queryandprocessdata/__init__.py
queryandprocessdata-0.0.2.dist-info/LICENCE.txt
queryandprocessdata-0.0.2.dist-info/METADATA
queryandprocessdata-0.0.2.dist-info/WHEEL
queryandprocessdata-0.0.2.dist-info/top_level.txt
queryandprocessdata-0.0.2.dist-info/RECORD
