Metadata-Version: 2.1
Name: queryandprocessdata
Version: 0.0.2
Summary: Proteus genProecess File
Home-page: UNKNOWN
Author: Proteus Technology PVT. LTD.
Author-email: <aniket.gadga@proteustech.in>
License: UNKNOWN
Keywords: python,first package
Platform: UNKNOWN
Classifier: Development Status :: 3 - Alpha
Classifier: Intended Audience :: Education
Classifier: Programming Language :: Python :: 2
Classifier: Programming Language :: Python :: 3
Classifier: Operating System :: MacOS :: MacOS X
Classifier: Operating System :: Microsoft :: Windows
License-File: LICENCE.txt
Requires-Dist: pandas
Requires-Dist: cx-Oracle
Requires-Dist: flask
Requires-Dist: datetime
Requires-Dist: pandarallel
Requires-Dist: numpy
Requires-Dist: loogerFile
Requires-Dist: pyodbc
